examples/todo/__init__.py
examples/todo/generate_output.py
examples/todo/wsgi.py
examples/todo/todo/__init__.py
examples/todo/todo/app.py
examples/todo/todo/converters.py
examples/todo/todo/database.py
examples/todo/todo/schemas.py
examples/todo/todo/handlers/__init__.py
examples/todo/todo/handlers/todo_handlers.py
flask_rebar/__init__.py
flask_rebar/compat.py
flask_rebar/errors.py
flask_rebar/messages.py
flask_rebar/py.typed
flask_rebar/rebar.py
flask_rebar/request_utils.py
flask_rebar/validation.py
flask_rebar/authenticators/__init__.py
flask_rebar/authenticators/base.py
flask_rebar/authenticators/header_api_key.py
flask_rebar/swagger_generation/__init__.py
flask_rebar/swagger_generation/authenticator_to_swagger.py
flask_rebar/swagger_generation/generator_utils.py
flask_rebar/swagger_generation/marshmallow_to_swagger.py
flask_rebar/swagger_generation/swagger_generator_base.py
flask_rebar/swagger_generation/swagger_generator_v2.py
flask_rebar/swagger_generation/swagger_generator_v3.py
flask_rebar/swagger_generation/swagger_objects.py
flask_rebar/swagger_generation/swagger_words.py
flask_rebar/swagger_generation/swagger_generator/__init__.py
flask_rebar/swagger_ui/__init__.py
flask_rebar/swagger_ui/blueprint.py
flask_rebar/swagger_ui/static/favicon-16x16.png
flask_rebar/swagger_ui/static/favicon-32x32.png
flask_rebar/swagger_ui/static/index.css
flask_rebar/swagger_ui/static/index.html
flask_rebar/swagger_ui/static/oauth2-redirect.html
flask_rebar/swagger_ui/static/swagger-initializer.js
flask_rebar/swagger_ui/static/swagger-ui-bundle.js
flask_rebar/swagger_ui/static/swagger-ui-bundle.js.map
flask_rebar/swagger_ui/static/swagger-ui-es-bundle-core.js
flask_rebar/swagger_ui/static/swagger-ui-es-bundle-core.js.map
flask_rebar/swagger_ui/static/swagger-ui-es-bundle.js
flask_rebar/swagger_ui/static/swagger-ui-es-bundle.js.map
flask_rebar/swagger_ui/static/swagger-ui-standalone-preset.js
flask_rebar/swagger_ui/static/swagger-ui-standalone-preset.js.map
flask_rebar-3.3.2.dist-info/AUTHORS
flask_rebar-3.3.2.dist-info/LICENSE
flask_rebar-3.3.2.dist-info/METADATA
flask_rebar-3.3.2.dist-info/WHEEL
flask_rebar-3.3.2.dist-info/top_level.txt
flask_rebar-3.3.2.dist-info/RECORD
