Metadata-Version: 2.1
Name: flask-rebar
Version: 3.3.2
Summary: Flask-Rebar combines flask, marshmallow, and swagger for robust REST services.
Home-page: https://github.com/plangrid/flask-rebar
Author: Barak Alon
Author-email: barak.s.alon@gmail.com
License: MIT
Keywords: flask,rest,marshmallow,openapi,swagger
Classifier: Environment :: Web Environment
Classifier: Framework :: Flask
Classifier: Intended Audience :: Developers
Classifier: License :: OSI Approved :: MIT License
Classifier: Operating System :: OS Independent
Classifier: Programming Language :: Python
Classifier: Programming Language :: Python :: 3.8
Classifier: Programming Language :: Python :: 3.9
Classifier: Programming Language :: Python :: 3.10
Classifier: Programming Language :: Python :: 3.11
Classifier: Topic :: Internet :: WWW/HTTP :: Dynamic Content
Classifier: Topic :: Internet :: WWW/HTTP :: WSGI :: Application
Classifier: Topic :: Software Development :: Libraries :: Application Frameworks
Classifier: Topic :: Software Development :: Libraries :: Python Modules
License-File: LICENSE
License-File: AUTHORS
Requires-Dist: Flask<4,>=1.0
Requires-Dist: marshmallow<4,>=3.0
Requires-Dist: typing-extensions<5,>=4.8; python_version < "3.10"
Requires-Dist: Werkzeug<4,>=2.2
Provides-Extra: dev
Requires-Dist: black==23.7.0; extra == "dev"
Requires-Dist: bumpversion==0.6.0; extra == "dev"
Requires-Dist: click<9.0.0,>=8.1.3; extra == "dev"
Requires-Dist: flake8==6.0.0; extra == "dev"
Requires-Dist: gitchangelog<4.0.0,>=3.0.4; extra == "dev"
Requires-Dist: jsonschema==4.18.4; extra == "dev"
Requires-Dist: marshmallow-objects~=2.3; extra == "dev"
Requires-Dist: mypy==1.8.0; extra == "dev"
Requires-Dist: parametrize==0.1.1; extra == "dev"
Requires-Dist: pre-commit>=1.14.4; extra == "dev"
Requires-Dist: pytest~=7.4; extra == "dev"
Requires-Dist: pytest-order~=1.0; extra == "dev"
Requires-Dist: Sphinx<7.0.0,>=6.0.0; extra == "dev"
Requires-Dist: sphinx_rtd_theme==1.2.2; extra == "dev"
Requires-Dist: types-jsonschema==4.17.0.10; extra == "dev"
Requires-Dist: types-setuptools==68.0.0.3; extra == "dev"
Requires-Dist: flask[async]<4,>=2; extra == "dev"
Provides-Extra: enum
Requires-Dist: marshmallow-enum~=1.5; extra == "enum"
Provides-Extra: async
Requires-Dist: flask[async]<4,>=2; extra == "async"
